pyrsdameraulevenshtein-1.2.0.dist-info/METADATA
pyrsdameraulevenshtein-1.2.0.dist-info/WHEEL
pyrsdameraulevenshtein-1.2.0.dist-info/licenses/LICENSE
pyrsdameraulevenshtein/__init__.py
pyrsdameraulevenshtein/pyrsdameraulevenshtein.cpython-314t-powerpc64le-linux-gnu.so
pyrsdameraulevenshtein-1.2.0.dist-info/RECORD
