Metadata-Version: 2.4
Name: pyrsdameraulevenshtein
Version: 1.2.0
Classifier: License :: OSI Approved :: GNU General Public License v3 (GPLv3)
Classifier: Topic :: Utilities
Classifier: Programming Language :: Rust
Classifier: Programming Language :: Python :: Implementation :: CPython
Classifier: Programming Language :: Python :: Implementation :: PyPy
Classifier: Programming Language :: Python :: 3
Classifier: Programming Language :: Python :: 3.11
Classifier: Programming Language :: Python :: 3.12
Classifier: Programming Language :: Python :: 3.13
Classifier: Programming Language :: Python :: 3.14
License-File: LICENSE
Summary: Damererau-Levenshtein implementation with Rust for high-performance.
Keywords: distance,rust,distance,dameraulevenshtein,damerau,levenshtein
Author-email: Jonas Blatt <jonas@blatts.de>
License: GPL-3.0-or-later
Requires-Python: >=3.11
Project-URL: homepage, https://github.com/joleaf/pyrsdameraulevenshtein
Project-URL: repository, https://github.com/joleaf/pyrsdameraulevenshtein
